{"1/0":{"name":"SingleTypeImportDeclaration","line":10,"column":0},"1":{"name":"ImportDeclarations","line":10,"column":0},"1":{"name":"ImportDeclarations","line":10,"column":0},"1":{"name":"ImportDeclarations","line":10,"column":0},"1":{"name":"ImportDeclarations","line":10,"column":0},"1":{"name":"ImportDeclarations","line":10,"column":0},"1":{"name":"ImportDeclarations","line":10,"column":0},"1/3":{"name":"SingleTypeImportDeclaration","line":13,"column":0},"2/0/0":{"name":"ClassSpecifier","line":46,"column":0},"2/0/0/0":{"name":"Implements","line":46,"column":26},"2/0/1":{"name":"ClassBody","line":47,"column":0},"2/0/1":{"name":"ClassBody","line":47,"column":0},"2/0/1":{"name":"ClassBody","line":47,"column":0},"2/0/1":{"name":"ClassBody","line":47,"column":0},"2/0/1":{"name":"ClassBody","line":47,"column":0},"2/0/1":{"name":"ClassBody","line":47,"column":0},"2/0/1":{"name":"ClassBody","line":47,"column":0},"2/0/1":{"name":"ClassBody","line":47,"column":0},"2/0/1":{"name":"ClassBody","line":47,"column":0},"2/0/1":{"name":"ClassBody","line":47,"column":0},"2/0/1":{"name":"ClassBody","line":47,"column":0},"2/0/1":{"name":"ClassBody","line":47,"column":0},"2/0/1":{"name":"ClassBody","line":47,"column":0},"2/0/1":{"name":"ClassBody","line":47,"column":0},"2/0/1":{"name":"ClassBody","line":47,"column":0},"2/0/1":{"name":"ClassBody","line":47,"column":0},"2/0/1":{"name":"ClassBody","line":47,"column":0},"2/0/1":{"name":"ClassBody","line":47,"column":0},"2/0/1":{"name":"ClassBody","line":47,"column":0},"2/0/1":{"name":"ClassBody","line":47,"column":0},"2/0/1":{"name":"ClassBody","line":47,"column":0},"2/0/1/0/0/0":{"name":"Protected","line":53,"column":4},"2/0/1/0":{"name":"FieldDeclaration","line":53,"column":4},"2/0/1/0":{"name":"FieldDeclaration","line":53,"column":4},"2/0/1/0":{"name":"FieldDeclaration","line":53,"column":4},"2/0/1/0/0":{"name":"Modifiers","line":53,"column":4},"2/0/1/0/0":{"name":"Modifiers","line":53,"column":4},"2/0/1/0/2":{"name":"VariableDeclarator","line":53,"column":27},"2/0/1/0/2":{"name":"VariableDeclarator","line":53,"column":27},"2/0/1/0/2/0":{"name":"NullLiteral","line":53,"column":36},"2/0/1/1":{"name":"FieldDeclaration","line":59,"column":4},"2/0/1/1":{"name":"FieldDeclaration","line":59,"column":4},"2/0/1/1":{"name":"FieldDeclaration","line":59,"column":4},"2/0/1/1/0":{"name":"Modifiers","line":59,"column":4},"2/0/1/1/0":{"name":"Modifiers","line":59,"column":4},"2/0/1/1/0/0":{"name":"Protected","line":59,"column":4},"2/0/1/1/2":{"name":"VariableDeclarator","line":59,"column":24},"2/0/1/2":{"name":"FieldDeclaration","line":64,"column":4},"2/0/1/3/0/0":{"name":"Protected","line":69,"column":4},"2/0/1/3":{"name":"FieldDeclaration","line":69,"column":4},"2/0/1/3":{"name":"FieldDeclaration","line":69,"column":4},"2/0/1/3":{"name":"FieldDeclaration","line":69,"column":4},"2/0/1/3/0":{"name":"Modifiers","line":69,"column":4},"2/0/1/3/0":{"name":"Modifiers","line":69,"column":4},"2/0/1/3/2":{"name":"VariableDeclarator","line":69,"column":28},"2/0/1/4/0/0":{"name":"Protected","line":71,"column":4},"2/0/1/4":{"name":"FieldDeclaration","line":71,"column":4},"2/0/1/4":{"name":"FieldDeclaration","line":71,"column":4},"2/0/1/4":{"name":"FieldDeclaration","line":71,"column":4},"2/0/1/4":{"name":"FieldDeclaration","line":71,"column":4},"2/0/1/4/0":{"name":"Modifiers","line":71,"column":4},"2/0/1/4/0":{"name":"Modifiers","line":71,"column":4},"2/0/1/4/1":{"name":"ReferenceType","line":71,"column":14},"2/0/1/4/2":{"name":"VariableDeclarator","line":71,"column":21},"2/0/1/5":{"name":"ConstructorDeclaration","line":73,"column":4},"2/0/1/5":{"name":"ConstructorDeclaration","line":73,"column":4},"2/0/1/5":{"name":"ConstructorDeclaration","line":73,"column":4},"2/0/1/5":{"name":"ConstructorDeclaration","line":73,"column":4},"2/0/1/5/0":{"name":"Parameters","line":73,"column":23},"2/0/1/5/0":{"name":"Parameters","line":73,"column":23},"2/0/1/5/0/0":{"name":"Parameter","line":73,"column":25},"2/0/1/5/0/0":{"name":"Parameter","line":73,"column":25},"2/0/1/5/0/0/0":{"name":"ReferenceType","line":73,"column":25},"2/0/1/5/1":{"name":"ConstructorBody","line":74,"column":4},"2/0/1/5/1/0/0":{"name":"FieldAccess","line":75,"column":8},"2/0/1/5/1/0/0":{"name":"FieldAccess","line":75,"column":8},"2/0/1/5/1/0/0/0":{"name":"This","line":75,"column":8},"2/0/1/5/1/0":{"name":"AssignStatement","line":75,"column":8},"2/0/1/5/1/0":{"name":"AssignStatement","line":75,"column":8},"2/0/1/5/1/0/1":{"name":"Name","line":75,"column":20},"2/0/1/5/1/1":{"name":"AssignStatement","line":76,"column":8},"2/0/1/5/1/1/0":{"name":"FieldAccess","line":76,"column":8},"2/0/1/5/1/1/0":{"name":"FieldAccess","line":76,"column":8},"2/0/1/5/1/1/0/0":{"name":"This","line":76,"column":8},"2/0/1/5/1/2/0":{"name":"FieldAccess","line":80,"column":8},"2/0/1/5/1/2":{"name":"AssignStatement","line":80,"column":8},"2/0/1/5/1/3":{"name":"PrimaryMethodInvocationStatement","line":81,"column":8},"2/0/1/5/1/3/0":{"name":"FieldAccess","line":81,"column":8},"2/0/1/5/1/3/1":{"name":"Arguments","line":81,"column":26},"2/0/1/5/1/3/1/0":{"name":"Name","line":81,"column":28},"2/0/1/5/1/3/1/0":{"name":"Name","line":81,"column":28},"2/0/1/6/0":{"name":"Modifiers","line":84,"column":4},"2/0/1/6/0":{"name":"Modifiers","line":84,"column":4},"2/0/1/6/0/0":{"name":"Protected","line":84,"column":4},"2/0/1/6/2/0":{"name":"TryStatement","line":86,"column":8},"2/0/1/6/2/0/1":{"name":"CatchClause","line":90,"column":8},"2/0/1/6/2/0/1":{"name":"CatchClause","line":90,"column":8},"2/0/1/6/2/0/1/0":{"name":"CatchParameter","line":90,"column":15},"2/0/1/6/2/0/1/0":{"name":"CatchParameter","line":90,"column":15},"2/0/1/6/2/0/1/0/0":{"name":"ReferenceType","line":90,"column":15},"2/0/1/6/2/0/1/1/0/0/1":{"name":"Arguments","line":92,"column":49},"2/0/1/6/2/0/1/1/0/0/1/0":{"name":"Name","line":92,"column":51},"2/0/1/7":{"name":"MethodDeclaration","line":101,"column":4},"2/0/1/8":{"name":"MethodDeclaration","line":110,"column":4},"2/0/1/9":{"name":"MethodDeclaration","line":120,"column":4},"2/0/1/9/4":{"name":"MethodBody","line":122,"column":4},"2/0/1/9/4":{"name":"MethodBody","line":122,"column":4},"2/0/1/9/4/0":{"name":"AssignStatement","line":123,"column":8},"2/0/1/9/4/0":{"name":"AssignStatement","line":123,"column":8},"46:0_-1":{"name":"PrimaryMethodInvocation","line":125,"column":30},"2/0/1/10":{"name":"MethodDeclaration","line":131,"column":4},"2/0/1/10/3":{"name":"MethodBody","line":133,"column":4},"2/0/1/10/3":{"name":"MethodBody","line":133,"column":4},"2/0/1/10/3/0":{"name":"SimpleMethodInvocationStatement","line":134,"column":8},"2/0/1/10/3/0":{"name":"SimpleMethodInvocationStatement","line":134,"column":8},"2/0/1/11/2":{"name":"MethodBody","line":142,"column":4},"2/0/1/11/2":{"name":"MethodBody","line":142,"column":4},"2/0/1/11/2/2":{"name":"LocalVariableDeclarationStatement","line":147,"column":8},"2/0/1/11/2/2/1":{"name":"VariableDeclarator","line":147,"column":17},"2/0/1/11/2/2/1":{"name":"VariableDeclarator","line":147,"column":17},"2/0/1/11/2/2/1/0/0":{"name":"FieldAccess","line":147,"column":24},"2/0/1/11/2/2/1/0":{"name":"PrimaryMethodInvocation","line":147,"column":24},"2/0/1/11/2/2/1/0":{"name":"PrimaryMethodInvocation","line":147,"column":24},"2/0/1/11/2/2/1/0":{"name":"PrimaryMethodInvocation","line":147,"column":24},"2/0/1/11/2/2/1/0":{"name":"PrimaryMethodInvocation","line":147,"column":24},"2/0/1/11/2/2/1/0/1":{"name":"Arguments","line":147,"column":41},"2/0/1/11/2/3":{"name":"LocalVariableDeclarationStatement","line":148,"column":8},"2/0/1/11/2/4/1/1/0/0":{"name":"PrimaryMethodInvocation","line":149,"column":61},"2/0/1/11/2/4/1/1/0/0/0":{"name":"Name","line":149,"column":61},"2/0/1/11/2/5/1/1/0/0":{"name":"PrimaryMethodInvocation","line":150,"column":62},"2/0/1/11/2/5/1/1/0/0/0":{"name":"FieldAccess","line":150,"column":62},"2/0/1/11/2/7/1/1/1/0/1":{"name":"PrimaryMethodInvocation","line":155,"column":37},"2/0/1/11/2/7/1/1/1/0/1/0":{"name":"FieldAccess","line":155,"column":37},"2/0/1/11/2/7/1/2/1/0/1":{"name":"PrimaryMethodInvocation","line":156,"column":43},"2/0/1/11/2/7/1/2/1/0/1/0":{"name":"Name","line":156,"column":43},"2/0/1/11/2/7/1/3/1/0/0/0":{"name":"FieldAccess","line":159,"column":16},"2/0/1/11/2/7/1/3/1/0/0":{"name":"PrimaryMethodInvocation","line":159,"column":16},"2/0/1/11/2/7/1/3/1/0/0":{"name":"PrimaryMethodInvocation","line":159,"column":16},"2/0/1/11/2/7/1/3/1/0":{"name":"PrimaryMethodInvocationStatement","line":159,"column":16},"2/0/1/11/2/7/1/12/3/0/0":{"name":"ReferenceType","line":172,"column":16},"2/0/1/11/2/7/1/12/3/0":{"name":"LocalVariableDeclarationStatement","line":172,"column":16},"2/0/1/11/2/7/1/12/3/0/1/0":{"name":"Cast","line":172,"column":45},"2/0/1/11/2/7/1/12/3/0/1/0/0":{"name":"ReferenceType","line":172,"column":46},"2/0/1/11/2/7/1/12/3/2/1/1/0":{"name":"Arguments","line":174,"column":58},"2/0/1/11/2/7/1/12/3/2/1/1/0/0":{"name":"FieldAccess","line":174,"column":60},"2/0/1/11/2/7/1/12/3/2/1/1/0/0":{"name":"FieldAccess","line":174,"column":60},"2/0/1/11/2/7/1/12/3/3/1":{"name":"Arguments","line":175,"column":34},"2/0/1/11/2/7/1/12/3/3/1/1":{"name":"FieldAccess","line":175,"column":47},"2/0/1/11/2/7/1/12/3/3/1/1":{"name":"FieldAccess","line":175,"column":47},"2/0/1/11/2/9":{"name":"IfStatement","line":183,"column":8},"2/0/1/11/2/9/0":{"name":"NotEq","line":183,"column":12},"2/0/1/11/2/9/0/0":{"name":"FieldAccess","line":183,"column":12},"2/0/1/11/2/9/1/1/0/0/1/1":{"name":"Arguments","line":188,"column":44},"2/0/1/11/2/9/1/1/0/0/1/1/0":{"name":"FieldAccess","line":188,"column":46},"2/0/1/11/2/9/1/1/1/1/0/0/0":{"name":"FieldAccess","line":195,"column":16},"2/0/1/11/2/9/1/1/1/1/0":{"name":"PrimaryMethodInvocationStatement","line":195,"column":16},"2/0/1/11/2/9/1/1/1/1/0/0":{"name":"PrimaryMethodInvocation","line":195,"column":16},"2/0/1/11/2/9/1/1/1/1/0/0":{"name":"PrimaryMethodInvocation","line":195,"column":16},"2/0/1/11/2/9/1/1/2/0":{"name":"Block","line":198,"column":12},"2/0/1/11/2/9/1/1/2/0/0":{"name":"IfStatement","line":199,"column":16},"2/0/1/11/2/9/1/1/2/0/0/0/0":{"name":"NotEq","line":199,"column":20},"2/0/1/11/2/9/1/1/2/0/0/0/0/0":{"name":"FieldAccess","line":199,"column":20},"2/0/1/11/2/9/1/1/2/0/0/0/1/0":{"name":"FieldAccess","line":199,"column":44},"2/0/1/11/2/9/1/1/2/0/0/0/1":{"name":"NotEq","line":199,"column":44},"2/0/1/12":{"name":"MethodDeclaration","line":223,"column":4},"2/0/1/12":{"name":"MethodDeclaration","line":223,"column":4},"2/0/1/12/2/1/0":{"name":"ReferenceType","line":223,"column":51},"2/0/1/12/2/1":{"name":"Parameter","line":223,"column":51},"2/0/1/12/3":{"name":"MethodBody","line":224,"column":4},"2/0/1/12/3/0/1/0/1":{"name":"PrimaryMethodInvocation","line":225,"column":42},"2/0/1/12/3/0/1/0/1/0":{"name":"FieldAccess","line":225,"column":42},"2/0/1/12/3/1/1/1/0":{"name":"FieldAccess","line":230,"column":12},"2/0/1/12/3/1/1/1":{"name":"PrimaryMethodInvocationStatement","line":230,"column":12},"2/0/1/13/0":{"name":"Modifiers","line":241,"column":4},"2/0/1/13/0":{"name":"Modifiers","line":241,"column":4},"2/0/1/13":{"name":"MethodDeclaration","line":241,"column":4},"2/0/1/13":{"name":"MethodDeclaration","line":241,"column":4},"2/0/1/13":{"name":"MethodDeclaration","line":241,"column":4},"2/0/1/13":{"name":"MethodDeclaration","line":241,"column":4},"2/0/1/13":{"name":"MethodDeclaration","line":241,"column":4},"2/0/1/13":{"name":"MethodDeclaration","line":241,"column":4},"2/0/1/13/0/0":{"name":"Protected","line":241,"column":4},"2/0/1/13/2":{"name":"Parameters","line":241,"column":30},"2/0/1/13/2":{"name":"Parameters","line":241,"column":30},"2/0/1/13/2/0":{"name":"Parameter","line":241,"column":32},"2/0/1/13/2/0":{"name":"Parameter","line":241,"column":32},"2/0/1/13/2/0/0":{"name":"ReferenceType","line":241,"column":32},"2/0/1/13/3":{"name":"Throws","line":242,"column":8},"2/0/1/13/4":{"name":"MethodBody","line":243,"column":4},"2/0/1/14/0":{"name":"Modifiers","line":253,"column":4},"2/0/1/14/0":{"name":"Modifiers","line":253,"column":4},"2/0/1/14":{"name":"MethodDeclaration","line":253,"column":4},"2/0/1/14":{"name":"MethodDeclaration","line":253,"column":4},"2/0/1/14":{"name":"MethodDeclaration","line":253,"column":4},"2/0/1/14":{"name":"MethodDeclaration","line":253,"column":4},"2/0/1/14/0/0":{"name":"Protected","line":253,"column":4},"2/0/1/14/2":{"name":"Parameters","line":253,"column":30},"2/0/1/14/2/0":{"name":"Parameter","line":253,"column":32},"2/0/1/14/3":{"name":"MethodBody","line":254,"column":4},"2/0/1/14/3/0":{"name":"LocalVariableDeclarationStatement","line":255,"column":8},"2/0/1/14/3/0/1":{"name":"VariableDeclarator","line":255,"column":18},"2/0/1/14/3/0/1/0":{"name":"PrimaryMethodInvocation","line":255,"column":28},"2/0/1/14/3/0/1/0":{"name":"PrimaryMethodInvocation","line":255,"column":28},"2/0/1/14/3/0/1/0/0":{"name":"FieldAccess","line":255,"column":28},"2/0/1/14/3/1/1":{"name":"Block","line":257,"column":8},"2/0/1/14/3/1/1":{"name":"Block","line":257,"column":8},"2/0/1/14/3/1/1":{"name":"Block","line":257,"column":8},"2/0/1/14/3/1/1":{"name":"Block","line":257,"column":8},"2/0/1/14/3/1/1/0":{"name":"LocalVariableDeclarationStatement","line":258,"column":12},"2/0/1/14/3/1/1/1":{"name":"LocalVariableDeclarationStatement","line":259,"column":12},"2/0/1/14/3/1/1/2":{"name":"LocalVariableDeclarationStatement","line":260,"column":12},"2/0/1/14/3/1/1/3/0":{"name":"Arguments","line":261,"column":29},"2/0/1/14/3/1/1/3/0":{"name":"Arguments","line":261,"column":29},"2/0/1/14/3/1/1/3/0":{"name":"Arguments","line":261,"column":29},"2/0/1/14/3/1/1/3/0/1":{"name":"TypeMethodInvocation","line":261,"column":37},"2/0/1/14/3/1/1/3/0/1":{"name":"TypeMethodInvocation","line":261,"column":37},"2/0/1/14/3/1/1/3/0/1":{"name":"TypeMethodInvocation","line":261,"column":37},"2/0/1/14/3/1/1/3/0/1/0":{"name":"Arguments","line":261,"column":59},"2/0/1/14/3/1/1/3/0/1/0":{"name":"Arguments","line":261,"column":59},"2/0/1/14/3/1/1/3/0/1/0":{"name":"Arguments","line":261,"column":59},"2/0/1/14/3/1/1/3/0/1/0/1":{"name":"Name","line":261,"column":70},"2/0/1/14/3/1/1/3/0/1/0/1":{"name":"Name","line":261,"column":70},"2/0/1/14/3/1/2/0/0":{"name":"PrimaryMethodInvocation","line":267,"column":12},"2/0/1/14/3/1/2/0/0":{"name":"PrimaryMethodInvocation","line":267,"column":12},"2/0/1/14/3/1/2/0/0/0":{"name":"FieldAccess","line":267,"column":12},"2/0/1/14/3/1/2/0":{"name":"PrimaryMethodInvocationStatement","line":267,"column":12}}