{"1":{"name":"ImportDeclarations","line":22,"column":0},"1":{"name":"ImportDeclarations","line":22,"column":0},"1":{"name":"ImportDeclarations","line":22,"column":0},"1":{"name":"ImportDeclarations","line":22,"column":0},"1":{"name":"ImportDeclarations","line":22,"column":0},"1":{"name":"ImportDeclarations","line":22,"column":0},"1/7":{"name":"SingleTypeImportDeclaration","line":29,"column":0},"1/8":{"name":"SingleTypeImportDeclaration","line":30,"column":0},"2/0/1":{"name":"ClassBody","line":42,"column":0},"2/0/1":{"name":"ClassBody","line":42,"column":0},"2/0/1":{"name":"ClassBody","line":42,"column":0},"2/0/1":{"name":"ClassBody","line":42,"column":0},"2/0/1":{"name":"ClassBody","line":42,"column":0},"2/0/1":{"name":"ClassBody","line":42,"column":0},"2/0/1":{"name":"ClassBody","line":42,"column":0},"2/0/1":{"name":"ClassBody","line":42,"column":0},"2/0/1":{"name":"ClassBody","line":42,"column":0},"2/0/1":{"name":"ClassBody","line":42,"column":0},"2/0/1":{"name":"ClassBody","line":42,"column":0},"2/0/1":{"name":"ClassBody","line":42,"column":0},"2/0/1":{"name":"ClassBody","line":42,"column":0},"2/0/1":{"name":"ClassBody","line":42,"column":0},"2/0/1":{"name":"ClassBody","line":42,"column":0},"2/0/1":{"name":"ClassBody","line":42,"column":0},"2/0/1":{"name":"ClassBody","line":42,"column":0},"2/0/1":{"name":"ClassBody","line":42,"column":0},"2/0/1":{"name":"ClassBody","line":42,"column":0},"2/0/1":{"name":"ClassBody","line":42,"column":0},"2/0/1":{"name":"ClassBody","line":42,"column":0},"2/0/1":{"name":"ClassBody","line":42,"column":0},"2/0/1":{"name":"ClassBody","line":42,"column":0},"2/0/1":{"name":"ClassBody","line":42,"column":0},"2/0/1":{"name":"ClassBody","line":42,"column":0},"2/0/1":{"name":"ClassBody","line":42,"column":0},"2/0/1":{"name":"ClassBody","line":42,"column":0},"2/0/1":{"name":"ClassBody","line":42,"column":0},"2/0/1":{"name":"ClassBody","line":42,"column":0},"2/0/1/0/0/0":{"name":"Public","line":49,"column":1},"2/0/1/0":{"name":"MethodDeclaration","line":49,"column":1},"2/0/1/0":{"name":"MethodDeclaration","line":49,"column":1},"2/0/1/0":{"name":"MethodDeclaration","line":49,"column":1},"2/0/1/0":{"name":"MethodDeclaration","line":49,"column":1},"2/0/1/0":{"name":"MethodDeclaration","line":49,"column":1},"2/0/1/0":{"name":"MethodDeclaration","line":49,"column":1},"2/0/1/0":{"name":"MethodDeclaration","line":49,"column":1},"2/0/1/0/0":{"name":"Modifiers","line":49,"column":1},"2/0/1/0/0":{"name":"Modifiers","line":49,"column":1},"2/0/1/0/0":{"name":"Modifiers","line":49,"column":1},"2/0/1/0/0":{"name":"Modifiers","line":49,"column":1},"2/0/1/0/0/1":{"name":"Static","line":49,"column":8},"2/0/1/0/0/1":{"name":"Static","line":49,"column":8},"2/0/1/0/1":{"name":"Void","line":49,"column":15},"2/0/1/0/1":{"name":"Void","line":49,"column":15},"2/0/1/0/2":{"name":"Parameters","line":49,"column":28},"2/0/1/0/2":{"name":"Parameters","line":49,"column":28},"2/0/1/0/2/0":{"name":"Parameter","line":49,"column":29},"2/0/1/0/2/0":{"name":"Parameter","line":49,"column":29},"2/0/1/0/2/0/0":{"name":"ReferenceType","line":49,"column":29},"2/0/1/0/3":{"name":"MethodBody","line":50,"column":1},"2/0/1/0/3":{"name":"MethodBody","line":50,"column":1},"2/0/1/0/3":{"name":"MethodBody","line":50,"column":1},"2/0/1/0/3":{"name":"MethodBody","line":50,"column":1},"62:0_-1":{"name":"Name","line":50,"column":17},"2/0/1/0/3/0/0":{"name":"ReferenceType","line":51,"column":2},"2/0/1/0/3/0":{"name":"LocalVariableDeclarationStatement","line":51,"column":2},"2/0/1/0/3/0":{"name":"LocalVariableDeclarationStatement","line":51,"column":2},"2/0/1/0/3/0":{"name":"LocalVariableDeclarationStatement","line":51,"column":2},"2/0/1/0/3/0/1":{"name":"VariableDeclarator","line":51,"column":9},"2/0/1/0/3/0/1":{"name":"VariableDeclarator","line":51,"column":9},"2/0/1/0/3/0/1":{"name":"VariableDeclarator","line":51,"column":9},"2/0/1/0/3/0/1/0":{"name":"PrimaryMethodInvocation","line":51,"column":20},"2/0/1/0/3/0/1/0":{"name":"PrimaryMethodInvocation","line":51,"column":20},"2/0/1/0/3/0/1/0":{"name":"PrimaryMethodInvocation","line":51,"column":20},"2/0/1/0/3/0/1/0":{"name":"PrimaryMethodInvocation","line":51,"column":20},"2/0/1/0/3/0/1/0":{"name":"PrimaryMethodInvocation","line":51,"column":20},"2/0/1/0/3/0/1/0":{"name":"PrimaryMethodInvocation","line":51,"column":20},"2/0/1/0/3/0/1/0/0":{"name":"FieldAccess","line":51,"column":20},"2/0/1/0/3/0/1/0/0":{"name":"FieldAccess","line":51,"column":20},"2/0/1/0/3/0/1/0/1":{"name":"Arguments","line":51,"column":47},"2/0/1/0/3/0/1/0/1":{"name":"Arguments","line":51,"column":47},"2/0/1/0/3/0/1/0/1":{"name":"Arguments","line":51,"column":47},"2/0/1/0/3/0/1/0/1":{"name":"Arguments","line":51,"column":47},"2/0/1/0/3/0/1/0/1/1":{"name":"StringLiteral","line":52,"column":24},"2/0/1/0/3/0/1/0/1/1":{"name":"StringLiteral","line":52,"column":24},"2/0/1/0/3/1":{"name":"AssignStatement","line":53,"column":2},"2/0/1/0/3/1":{"name":"AssignStatement","line":53,"column":2},"2/0/1/0/3/2":{"name":"TryStatement","line":54,"column":2},"2/0/1/0/3/2/0":{"name":"Block","line":55,"column":2},"m133:0_-1":{"name":"Modifiers","line":56,"column":1},"m133:0_-2":{"name":"Modifiers","line":56,"column":1},"2/0/1/0/3/2/0/0":{"name":"SimpleMethodInvocationStatement","line":56,"column":3},"2/0/1/0/3/2/0/0":{"name":"SimpleMethodInvocationStatement","line":56,"column":3},"2/0/1/0/3/2/0/0/0":{"name":"Arguments","line":56,"column":10},"2/0/1/0/3/2/0/0/0":{"name":"Arguments","line":56,"column":10},"2/0/1/0/3/2/0/0/0/0":{"name":"StandardInstanceCreation","line":56,"column":11},"2/0/1/0/3/2/0/0/0/0":{"name":"StandardInstanceCreation","line":56,"column":11},"2/0/1/0/3/2/0/0/0/0":{"name":"StandardInstanceCreation","line":56,"column":11},"2/0/1/0/3/2/0/0/0/0/0":{"name":"ReferenceType","line":56,"column":15},"2/0/1/0/3/2/0/0/0/0/1":{"name":"Arguments","line":56,"column":18},"2/0/1/0/3/2/0/0/0/0/1":{"name":"Arguments","line":56,"column":18},"2/0/1/0/3/2/0/0/0/0/1/0":{"name":"Add","line":56,"column":19},"2/0/1/0/3/2/0/0/0/0/1/0":{"name":"Add","line":56,"column":19},"2/0/1/0/3/2/0/0/0/0/1/0":{"name":"Add","line":56,"column":19},"2/0/1/0/3/2/0/0/0/0/1/0":{"name":"Add","line":56,"column":19},"2/0/1/0/3/2/0/0/0/0/1/0":{"name":"Add","line":56,"column":19},"2/0/1/0/3/2/0/0/0/0/1/0/0":{"name":"Add","line":56,"column":19},"2/0/1/0/3/2/0/0/0/0/1/0/0":{"name":"Add","line":56,"column":19},"2/0/1/0/3/2/0/0/0/0/1/0/0":{"name":"Add","line":56,"column":19},"2/0/1/0/3/2/0/0/0/0/1/0/0":{"name":"Add","line":56,"column":19},"2/0/1/0/3/2/0/0/0/0/1/0/0/0":{"name":"Add","line":56,"column":19},"2/0/1/0/3/2/0/0/0/0/1/0/0/0":{"name":"Add","line":56,"column":19},"2/0/1/0/3/2/0/0/0/0/1/0/0/0":{"name":"Add","line":56,"column":19},"2/0/1/0/3/2/0/0/0/0/1/0/0/0":{"name":"Add","line":56,"column":19},"2/0/1/0/3/2/0/0/0/0/1/0/0/0":{"name":"Add","line":56,"column":19},"2/0/1/0/3/2/0/0/0/0/1/0/0/0/1":{"name":"Name","line":56,"column":29},"2/0/1/0/3/2/0/0/0/0/1/0/0/0/1":{"name":"Name","line":56,"column":29},"2/0/1/0/3/2/0/0/0/0/1/0/0/0/1":{"name":"Name","line":56,"column":29},"2/0/1/0/3/2/0/0/0/0/1/0/1":{"name":"Name","line":56,"column":46},"2/0/1/0/3/2/0/0/0/0/1/0/1":{"name":"Name","line":56,"column":46},"2/0/1/0/3/2/1":{"name":"CatchClause","line":58,"column":2},"2/0/1/0/3/2/1/0":{"name":"CatchParameter","line":58,"column":8},"2/0/1/0/3/2/1/0/0":{"name":"ReferenceType","line":58,"column":8},"2/0/1/0/3/2/1/1/0/0":{"name":"Arguments","line":60,"column":10},"2/0/1/0/3/2/1/1/0/0/1":{"name":"ClassLiteral","line":60,"column":21},"2/0/1/0/3/2/1/1/0/0/1":{"name":"ClassLiteral","line":60,"column":21},"2/0/1/0/3/2/1/1/0/0/1":{"name":"ClassLiteral","line":60,"column":21},"2/0/1/0/3/2/1/1/0/0/1/0":{"name":"ReferenceType","line":60,"column":21},"2/0/1/0/3/2/1/1/0/0/1/0":{"name":"ReferenceType","line":60,"column":21},"33:2/0_-1":{"name":"SuperInvocation","line":67,"column":2},"33:2/0_-3":{"name":"SuperInvocation","line":67,"column":2},"33:2/0_-2":{"name":"SuperInvocation","line":67,"column":2},"33:2/1_-2":{"name":"SimpleMethodInvocationStatement","line":69,"column":2},"33:2/1_-4":{"name":"SimpleMethodInvocationStatement","line":69,"column":2},"33:2/1_-32":{"name":"SimpleMethodInvocationStatement","line":69,"column":2},"33:2/1_-3":{"name":"SimpleMethodInvocationStatement","line":69,"column":2},"33:2/1_-14":{"name":"SimpleMethodInvocationStatement","line":69,"column":2},"33:2/1_-12":{"name":"SimpleMethodInvocationStatement","line":69,"column":2},"33:2/1_-29":{"name":"SimpleMethodInvocationStatement","line":69,"column":2},"33:2/1_-11":{"name":"SimpleMethodInvocationStatement","line":69,"column":2},"33:2/1_-8":{"name":"SimpleMethodInvocationStatement","line":69,"column":2},"33:2/1_-20":{"name":"SimpleMethodInvocationStatement","line":69,"column":2},"33:2/1_-5":{"name":"SimpleMethodInvocationStatement","line":69,"column":2},"33:2/1_-1":{"name":"SimpleMethodInvocationStatement","line":69,"column":2},"33:2/1_-22":{"name":"SimpleMethodInvocationStatement","line":69,"column":2},"33:2/1_-9":{"name":"SimpleMethodInvocationStatement","line":69,"column":2},"33:2/1_-6":{"name":"SimpleMethodInvocationStatement","line":69,"column":2},"33:2/1_-28":{"name":"SimpleMethodInvocationStatement","line":69,"column":2},"33:2/1_-33":{"name":"SimpleMethodInvocationStatement","line":69,"column":2},"33:2/1_-23":{"name":"SimpleMethodInvocationStatement","line":69,"column":2},"33:2/1_-31":{"name":"SimpleMethodInvocationStatement","line":69,"column":2},"33:2/1_-18":{"name":"SimpleMethodInvocationStatement","line":69,"column":2},"33:2/1_-13":{"name":"SimpleMethodInvocationStatement","line":69,"column":2},"33:2/1_-16":{"name":"SimpleMethodInvocationStatement","line":69,"column":2},"33:2/1_-24":{"name":"SimpleMethodInvocationStatement","line":69,"column":2},"33:2/1_-7":{"name":"SimpleMethodInvocationStatement","line":69,"column":2},"33:2/1_-26":{"name":"SimpleMethodInvocationStatement","line":69,"column":2},"33:2/1_-21":{"name":"SimpleMethodInvocationStatement","line":69,"column":2},"33:2/1_-25":{"name":"SimpleMethodInvocationStatement","line":69,"column":2},"33:2/1_-19":{"name":"SimpleMethodInvocationStatement","line":69,"column":2},"33:2/1_-30":{"name":"SimpleMethodInvocationStatement","line":69,"column":2},"33:2/1_-15":{"name":"SimpleMethodInvocationStatement","line":69,"column":2},"33:2/1_-17":{"name":"SimpleMethodInvocationStatement","line":69,"column":2},"33:2/1_-27":{"name":"SimpleMethodInvocationStatement","line":69,"column":2},"33:2/1_-10":{"name":"SimpleMethodInvocationStatement","line":69,"column":2},"2/0/1/1/3/0/1":{"name":"Arguments","line":72,"column":16},"2/0/1/1/3/0/1/0":{"name":"Name","line":72,"column":17},"2/0/1/2":{"name":"ConstructorDeclaration","line":80,"column":1},"2/0/1/2":{"name":"ConstructorDeclaration","line":80,"column":1},"2/0/1/2":{"name":"ConstructorDeclaration","line":80,"column":1},"2/0/1/2":{"name":"ConstructorDeclaration","line":80,"column":1},"2/0/1/2/0":{"name":"Modifiers","line":80,"column":1},"2/0/1/2/0":{"name":"Modifiers","line":80,"column":1},"33:2/8_-4":{"name":"LocalVariableDeclarationStatement","line":80,"column":2},"33:2/8_-3":{"name":"LocalVariableDeclarationStatement","line":80,"column":2},"33:2/8_-2":{"name":"LocalVariableDeclarationStatement","line":80,"column":2},"33:2/8_-1":{"name":"LocalVariableDeclarationStatement","line":80,"column":2},"2/0/1/2/1":{"name":"Parameters","line":80,"column":18},"2/0/1/2/1":{"name":"Parameters","line":80,"column":18},"2/0/1/2/2":{"name":"ConstructorBody","line":81,"column":1},"2/0/1/2/2":{"name":"ConstructorBody","line":81,"column":1},"2/0/1/2/2":{"name":"ConstructorBody","line":81,"column":1},"2/0/1/2/2":{"name":"ConstructorBody","line":81,"column":1},"2/0/1/2/2":{"name":"ConstructorBody","line":81,"column":1},"2/0/1/2/2":{"name":"ConstructorBody","line":81,"column":1},"2/0/1/2/2":{"name":"ConstructorBody","line":81,"column":1},"2/0/1/2/2":{"name":"ConstructorBody","line":81,"column":1},"2/0/1/2/2":{"name":"ConstructorBody","line":81,"column":1},"2/0/1/2/2":{"name":"ConstructorBody","line":81,"column":1},"2/0/1/2/2":{"name":"ConstructorBody","line":81,"column":1},"2/0/1/2/2":{"name":"ConstructorBody","line":81,"column":1},"2/0/1/2/2":{"name":"ConstructorBody","line":81,"column":1},"2/0/1/2/2":{"name":"ConstructorBody","line":81,"column":1},"2/0/1/2/2":{"name":"ConstructorBody","line":81,"column":1},"2/0/1/2/2":{"name":"ConstructorBody","line":81,"column":1},"2/0/1/2/2":{"name":"ConstructorBody","line":81,"column":1},"2/0/1/2/2":{"name":"ConstructorBody","line":81,"column":1},"2/0/1/2/2":{"name":"ConstructorBody","line":81,"column":1},"2/0/1/2/2":{"name":"ConstructorBody","line":81,"column":1},"2/0/1/2/2":{"name":"ConstructorBody","line":81,"column":1},"2/0/1/2/2":{"name":"ConstructorBody","line":81,"column":1},"2/0/1/2/2":{"name":"ConstructorBody","line":81,"column":1},"2/0/1/2/2":{"name":"ConstructorBody","line":81,"column":1},"2/0/1/2/2":{"name":"ConstructorBody","line":81,"column":1},"2/0/1/2/2":{"name":"ConstructorBody","line":81,"column":1},"2/0/1/2/2":{"name":"ConstructorBody","line":81,"column":1},"2/0/1/2/2":{"name":"ConstructorBody","line":81,"column":1},"2/0/1/2/2":{"name":"ConstructorBody","line":81,"column":1},"2/0/1/2/2":{"name":"ConstructorBody","line":81,"column":1},"2/0/1/2/2":{"name":"ConstructorBody","line":81,"column":1},"2/0/1/2/2":{"name":"ConstructorBody","line":81,"column":1},"2/0/1/2/2":{"name":"ConstructorBody","line":81,"column":1},"2/0/1/2/2":{"name":"ConstructorBody","line":81,"column":1},"2/0/1/2/2":{"name":"ConstructorBody","line":81,"column":1},"2/0/1/2/2":{"name":"ConstructorBody","line":81,"column":1},"2/0/1/2/2":{"name":"ConstructorBody","line":81,"column":1},"2/0/1/2/2":{"name":"ConstructorBody","line":81,"column":1},"2/0/1/2/2":{"name":"ConstructorBody","line":81,"column":1},"2/0/1/2/2":{"name":"ConstructorBody","line":81,"column":1},"2/0/1/2/2":{"name":"ConstructorBody","line":81,"column":1},"2/0/1/2/2":{"name":"ConstructorBody","line":81,"column":1},"2/0/1/2/2":{"name":"ConstructorBody","line":81,"column":1},"2/0/1/2/2":{"name":"ConstructorBody","line":81,"column":1},"2/0/1/2/2":{"name":"ConstructorBody","line":81,"column":1},"2/0/1/2/2":{"name":"ConstructorBody","line":81,"column":1},"2/0/1/2/2":{"name":"ConstructorBody","line":81,"column":1},"33:2/9_2":{"name":"PrimaryMethodInvocationStatement","line":81,"column":2},"33:2/9_6":{"name":"PrimaryMethodInvocationStatement","line":81,"column":2},"33:2/9_3":{"name":"PrimaryMethodInvocationStatement","line":81,"column":2},"33:2/9_1":{"name":"PrimaryMethodInvocationStatement","line":81,"column":2},"33:2/9_4":{"name":"PrimaryMethodInvocationStatement","line":81,"column":2},"33:2/9_5":{"name":"PrimaryMethodInvocationStatement","line":81,"column":2},"2/0/1/2/2/0":{"name":"SuperInvocation","line":82,"column":2},"2/0/1/2/2/0":{"name":"SuperInvocation","line":82,"column":2},"2/0/1/2/2/1":{"name":"SimpleMethodInvocationStatement","line":84,"column":2},"2/0/1/2/2/1":{"name":"SimpleMethodInvocationStatement","line":84,"column":2},"2/0/1/2/2/2":{"name":"AssignStatement","line":86,"column":2},"2/0/1/2/2/2":{"name":"AssignStatement","line":86,"column":2},"2/0/1/2/2/2/1":{"name":"ArrayCreationDims","line":86,"column":12},"2/0/1/2/2/2/1/0":{"name":"ReferenceType","line":86,"column":16},"2/0/1/2/2/3":{"name":"LocalVariableDeclarationStatement","line":88,"column":2},"2/0/1/2/2/3":{"name":"LocalVariableDeclarationStatement","line":88,"column":2},"2/0/1/2/2/4":{"name":"LocalVariableDeclarationStatement","line":90,"column":2},"2/0/1/2/2/4":{"name":"LocalVariableDeclarationStatement","line":90,"column":2},"2/0/1/2/2/5":{"name":"PrimaryMethodInvocationStatement","line":91,"column":2},"2/0/1/2/2/5":{"name":"PrimaryMethodInvocationStatement","line":91,"column":2},"2/0/1/2/2/6":{"name":"PrimaryMethodInvocationStatement","line":92,"column":2},"2/0/1/2/2/6":{"name":"PrimaryMethodInvocationStatement","line":92,"column":2},"2/0/1/2/2/7":{"name":"LocalVariableDeclarationStatement","line":94,"column":2},"2/0/1/2/2/7":{"name":"LocalVariableDeclarationStatement","line":94,"column":2},"2/0/1/2/2/8":{"name":"PrimaryMethodInvocationStatement","line":95,"column":2},"2/0/1/2/2/8":{"name":"PrimaryMethodInvocationStatement","line":95,"column":2},"2/0/1/2/2/8/1/0/1":{"name":"Arguments","line":95,"column":33},"2/0/1/2/2/8/1/0/1/1":{"name":"IntegerLiteral","line":95,"column":36},"2/0/1/2/2/9":{"name":"PrimaryMethodInvocationStatement","line":96,"column":2},"2/0/1/2/2/9":{"name":"PrimaryMethodInvocationStatement","line":96,"column":2},"2/0/1/2/2/10":{"name":"LocalVariableDeclarationStatement","line":97,"column":2},"2/0/1/2/2/10":{"name":"LocalVariableDeclarationStatement","line":97,"column":2},"2/0/1/2/2/11":{"name":"PrimaryMethodInvocationStatement","line":98,"column":2},"2/0/1/2/2/11":{"name":"PrimaryMethodInvocationStatement","line":98,"column":2},"2/0/1/2/2/12":{"name":"AssignStatement","line":99,"column":2},"2/0/1/2/2/12":{"name":"AssignStatement","line":99,"column":2},"2/0/1/2/2/13":{"name":"PrimaryMethodInvocationStatement","line":100,"column":2},"2/0/1/2/2/13":{"name":"PrimaryMethodInvocationStatement","line":100,"column":2},"2/0/1/2/2/14":{"name":"LocalVariableDeclarationStatement","line":101,"column":2},"2/0/1/2/2/14":{"name":"LocalVariableDeclarationStatement","line":101,"column":2},"2/0/1/2/2/15":{"name":"AssignStatement","line":102,"column":2},"2/0/1/2/2/15":{"name":"AssignStatement","line":102,"column":2},"2/0/1/2/2/16":{"name":"PrimaryMethodInvocationStatement","line":103,"column":2},"2/0/1/2/2/16":{"name":"PrimaryMethodInvocationStatement","line":103,"column":2},"2/0/1/2/2/17":{"name":"PrimaryMethodInvocationStatement","line":104,"column":2},"2/0/1/2/2/17":{"name":"PrimaryMethodInvocationStatement","line":104,"column":2},"2/0/1/2/2/18":{"name":"PrimaryMethodInvocationStatement","line":105,"column":2},"2/0/1/2/2/18":{"name":"PrimaryMethodInvocationStatement","line":105,"column":2},"2/0/1/2/2/19":{"name":"PrimaryMethodInvocationStatement","line":106,"column":2},"2/0/1/2/2/19":{"name":"PrimaryMethodInvocationStatement","line":106,"column":2},"2/0/1/2/2/20":{"name":"PrimaryMethodInvocationStatement","line":108,"column":2},"2/0/1/2/2/20":{"name":"PrimaryMethodInvocationStatement","line":108,"column":2},"2/0/1/2/2/21":{"name":"LocalVariableDeclarationStatement","line":110,"column":2},"2/0/1/2/2/21":{"name":"LocalVariableDeclarationStatement","line":110,"column":2},"2/0/1/2/2/22":{"name":"PrimaryMethodInvocationStatement","line":111,"column":2},"2/0/1/2/2/22":{"name":"PrimaryMethodInvocationStatement","line":111,"column":2},"2/0/1/2/2/23":{"name":"PrimaryMethodInvocationStatement","line":112,"column":2},"2/0/1/2/2/23":{"name":"PrimaryMethodInvocationStatement","line":112,"column":2},"2/0/1/2/2/24":{"name":"AssignStatement","line":113,"column":2},"2/0/1/2/2/24":{"name":"AssignStatement","line":113,"column":2},"2/0/1/2/2/25":{"name":"PrimaryMethodInvocationStatement","line":114,"column":2},"2/0/1/2/2/25":{"name":"PrimaryMethodInvocationStatement","line":114,"column":2},"2/0/1/2/2/26":{"name":"PrimaryMethodInvocationStatement","line":115,"column":2},"2/0/1/2/2/26":{"name":"PrimaryMethodInvocationStatement","line":115,"column":2},"2/0/1/2/2/27":{"name":"PrimaryMethodInvocationStatement","line":116,"column":2},"2/0/1/2/2/27":{"name":"PrimaryMethodInvocationStatement","line":116,"column":2},"2/0/1/2/2/28":{"name":"PrimaryMethodInvocationStatement","line":117,"column":2},"2/0/1/2/2/28":{"name":"PrimaryMethodInvocationStatement","line":117,"column":2},"2/0/1/2/2/29":{"name":"AssignStatement","line":118,"column":2},"2/0/1/2/2/29":{"name":"AssignStatement","line":118,"column":2},"2/0/1/2/2/30":{"name":"PrimaryMethodInvocationStatement","line":119,"column":2},"2/0/1/2/2/30":{"name":"PrimaryMethodInvocationStatement","line":119,"column":2},"2/0/1/2/2/31":{"name":"PrimaryMethodInvocationStatement","line":120,"column":2},"2/0/1/2/2/31":{"name":"PrimaryMethodInvocationStatement","line":120,"column":2},"2/0/1/2/2/32":{"name":"PrimaryMethodInvocationStatement","line":121,"column":2},"2/0/1/2/2/32":{"name":"PrimaryMethodInvocationStatement","line":121,"column":2},"2/0/1/2/2/33":{"name":"PrimaryMethodInvocationStatement","line":122,"column":2},"2/0/1/2/2/33":{"name":"PrimaryMethodInvocationStatement","line":122,"column":2},"2/0/1/2/2/34":{"name":"PrimaryMethodInvocationStatement","line":123,"column":2},"2/0/1/2/2/34":{"name":"PrimaryMethodInvocationStatement","line":123,"column":2},"2/0/1/2/2/35":{"name":"PrimaryMethodInvocationStatement","line":125,"column":2},"2/0/1/2/2/35":{"name":"PrimaryMethodInvocationStatement","line":125,"column":2},"2/0/1/2/2/36":{"name":"AssignStatement","line":127,"column":2},"2/0/1/2/2/36":{"name":"AssignStatement","line":127,"column":2},"2/0/1/2/2/37":{"name":"PrimaryMethodInvocationStatement","line":128,"column":2},"2/0/1/2/2/37":{"name":"PrimaryMethodInvocationStatement","line":128,"column":2},"2/0/1/2/2/38":{"name":"PrimaryMethodInvocationStatement","line":129,"column":2},"2/0/1/2/2/38":{"name":"PrimaryMethodInvocationStatement","line":129,"column":2},"2/0/1/2/2/39":{"name":"PrimaryMethodInvocationStatement","line":130,"column":2},"2/0/1/2/2/39":{"name":"PrimaryMethodInvocationStatement","line":130,"column":2},"2/0/1/2/2/40":{"name":"PrimaryMethodInvocationStatement","line":131,"column":2},"2/0/1/2/2/40":{"name":"PrimaryMethodInvocationStatement","line":131,"column":2},"2/0/1/2/2/40/1":{"name":"Arguments","line":131,"column":22},"2/0/1/2/2/40/1":{"name":"Arguments","line":131,"column":22},"2/0/1/2/2/40/1/1":{"name":"StandardInstanceCreation","line":131,"column":43},"2/0/1/2/2/41":{"name":"SimpleMethodInvocationStatement","line":133,"column":2},"2/0/1/2/2/41":{"name":"SimpleMethodInvocationStatement","line":133,"column":2},"2/0/1/2/2/42":{"name":"SimpleMethodInvocationStatement","line":135,"column":2},"2/0/1/2/2/42":{"name":"SimpleMethodInvocationStatement","line":135,"column":2},"2/0/1/2/2/43":{"name":"SimpleMethodInvocationStatement","line":137,"column":2},"2/0/1/2/2/43":{"name":"SimpleMethodInvocationStatement","line":137,"column":2},"2/0/1/2/2/43/0":{"name":"Arguments","line":137,"column":9},"2/0/1/2/2/43/0/0":{"name":"IntegerLiteral","line":137,"column":10},"2/0/1/2/2/44":{"name":"PrimaryMethodInvocationStatement","line":138,"column":2},"2/0/1/2/2/44":{"name":"PrimaryMethodInvocationStatement","line":138,"column":2},"2/0/1/2/2/45":{"name":"SimpleMethodInvocationStatement","line":140,"column":2},"2/0/1/2/2/45":{"name":"SimpleMethodInvocationStatement","line":140,"column":2},"2/0/1/3":{"name":"MethodDeclaration","line":149,"column":1},"2/0/1/3":{"name":"MethodDeclaration","line":149,"column":1},"2/0/1/3/2/0":{"name":"Parameter","line":149,"column":21},"2/0/1/3/2/0/0":{"name":"ReferenceType","line":149,"column":21},"2/0/1/3/3":{"name":"MethodBody","line":150,"column":1},"2/0/1/3/3":{"name":"MethodBody","line":150,"column":1},"2/0/1/3/3":{"name":"MethodBody","line":150,"column":1},"2/0/1/3/3":{"name":"MethodBody","line":150,"column":1},"2/0/1/3/3":{"name":"MethodBody","line":150,"column":1},"2/0/1/3/3":{"name":"MethodBody","line":150,"column":1},"2/0/1/3/3/1":{"name":"TryStatement","line":155,"column":2},"2/0/1/3/3/1":{"name":"TryStatement","line":155,"column":2},"2/0/1/3/3/1/0/0/1":{"name":"Arguments","line":157,"column":19},"2/0/1/3/3/1/0/0/1/0":{"name":"PrimaryMethodInvocation","line":157,"column":20},"2/0/1/3/3/1/0/0/1/0":{"name":"PrimaryMethodInvocation","line":157,"column":20},"2/0/1/3/3/1/0/0/1/0/0":{"name":"Name","line":157,"column":20},"2/0/1/3/3/1/0/1/1":{"name":"Arguments","line":158,"column":17},"2/0/1/3/3/1/0/1/1/0":{"name":"Name","line":158,"column":18},"m191:1/0":{"name":"Name","line":164,"column":26},"2/0/1/9":{"name":"FieldDeclaration","line":191,"column":1},"2/0/1/9/1":{"name":"ReferenceType","line":191,"column":9},"2/0/1/11/1/0/3/1/1/0/2/0":{"name":"LocalVariableDeclarationStatement","line":205,"column":5},"2/0/1/11/1/0/3/1/1/0/2/0/0":{"name":"ReferenceType","line":205,"column":5},"2/0/1/11/1/0/3/1/2/1/0/2/0/0":{"name":"ReferenceType","line":215,"column":5},"2/0/1/11/1/0/3/1/2/1/0/2/0":{"name":"LocalVariableDeclarationStatement","line":215,"column":5},"2/0/1/12/1/0/3/0/1/0/2/1/1/0":{"name":"Arguments","line":244,"column":13},"2/0/1/12/1/0/3/0/1/0/2/1/1/0/0":{"name":"Name","line":244,"column":14},"2/0/1/13/1/0/3/0/1":{"name":"Block","line":261,"column":3},"2/0/1/13/1/0/3/0/1/0":{"name":"TryStatement","line":262,"column":4},"2/0/1/13/1/0/3/0/1/0":{"name":"TryStatement","line":262,"column":4},"2/0/1/13/1/0/3/0/1/0":{"name":"TryStatement","line":262,"column":4},"2/0/1/13/1/0/3/0/1/0":{"name":"TryStatement","line":262,"column":4},"2/0/1/13/1/0/3/0/1/0/0":{"name":"Block","line":263,"column":4},"2/0/1/13/1/0/3/0/1/0/0/0":{"name":"SimpleMethodInvocationStatement","line":264,"column":5},"2/0/1/13/1/0/3/0/1/0/0/0/0":{"name":"Arguments","line":264,"column":12},"2/0/1/13/1/0/3/0/1/0/0/0/0/0":{"name":"StandardInstanceCreation","line":264,"column":13},"2/0/1/13/1/0/3/0/1/0/0/0/0/0/1":{"name":"Arguments","line":264,"column":20},"2/0/1/13/1/0/3/0/1/0/0/0/0/0/1/0":{"name":"PrimaryMethodInvocation","line":264,"column":21},"2/0/1/13/1/0/3/0/1/0/1":{"name":"CatchClause","line":267,"column":4},"2/0/1/13/1/0/3/0/1/0/1":{"name":"CatchClause","line":267,"column":4},"2/0/1/13/1/0/3/0/1/0/1":{"name":"CatchClause","line":267,"column":4},"2/0/1/13/1/0/3/0/1/0/1":{"name":"CatchClause","line":267,"column":4},"2/0/1/13/1/0/3/0/1/0/1/0":{"name":"CatchParameter","line":267,"column":10},"2/0/1/13/1/0/3/0/1/0/1/1/0/0":{"name":"Arguments","line":269,"column":12},"2/0/1/13/1/0/3/0/1/0/1/1/0/0/2":{"name":"Name","line":269,"column":28},"2/0/1/13/1/0/3/0/1/0/1/1/1/1/0":{"name":"ArrayInitializer","line":270,"column":21},"2/0/1/13/1/0/3/0/1/0/1/1/1/1/0/0":{"name":"PrimaryMethodInvocation","line":270,"column":23},"2/0/1/13/1/0/3/0/1/0/1/1/1/1/0/0":{"name":"PrimaryMethodInvocation","line":270,"column":23},"2/0/1/13/1/0/3/0/1/0/1/1/1/1/0/0":{"name":"PrimaryMethodInvocation","line":270,"column":23},"2/0/1/13/1/0/3/0/1/0/1/1/1/1/0/0/0":{"name":"FieldAccess","line":270,"column":23},"2/0/1/13/1/0/3/0/1/0/1/1/1/1/0/0/1":{"name":"Arguments","line":270,"column":39},"2/0/1/13/1/0/3/0/1/0/1/1/2/1":{"name":"Arguments","line":271,"column":23},"2/0/1/13/1/0/3/0/1/0/1/1/2/1/0":{"name":"QualifiedThis","line":271,"column":24},"37:0_-1":{"name":"Name","line":562,"column":14}}