{"1":{"name":"ImportDeclarations","line":10,"column":0},"1":{"name":"ImportDeclarations","line":10,"column":0},"1":{"name":"ImportDeclarations","line":10,"column":0},"1/2":{"name":"SingleTypeImportDeclaration","line":12,"column":0},"2/0/1":{"name":"ClassBody","line":31,"column":0},"2/0/1":{"name":"ClassBody","line":31,"column":0},"2/0/1":{"name":"ClassBody","line":31,"column":0},"2/0/1":{"name":"ClassBody","line":31,"column":0},"2/0/1":{"name":"ClassBody","line":31,"column":0},"2/0/1":{"name":"ClassBody","line":31,"column":0},"2/0/1":{"name":"ClassBody","line":31,"column":0},"2/0/1":{"name":"ClassBody","line":31,"column":0},"2/0/1":{"name":"ClassBody","line":31,"column":0},"2/0/1":{"name":"ClassBody","line":31,"column":0},"2/0/1/0":{"name":"FieldDeclaration","line":32,"column":4},"2/0/1/0":{"name":"FieldDeclaration","line":32,"column":4},"2/0/1/0":{"name":"FieldDeclaration","line":32,"column":4},"2/0/1/0/0":{"name":"Modifiers","line":32,"column":4},"2/0/1/0/2":{"name":"VariableDeclarator","line":32,"column":19},"2/0/1/1":{"name":"FieldDeclaration","line":33,"column":4},"2/0/1/1":{"name":"FieldDeclaration","line":33,"column":4},"2/0/1/1":{"name":"FieldDeclaration","line":33,"column":4},"2/0/1/1/0":{"name":"Modifiers","line":33,"column":4},"2/0/1/1/2":{"name":"VariableDeclarator","line":33,"column":19},"2/0/1/2":{"name":"FieldDeclaration","line":34,"column":4},"2/0/1/2":{"name":"FieldDeclaration","line":34,"column":4},"2/0/1/2":{"name":"FieldDeclaration","line":34,"column":4},"2/0/1/2/0":{"name":"Modifiers","line":34,"column":4},"2/0/1/2/2":{"name":"VariableDeclarator","line":34,"column":17},"2/0/1/3":{"name":"FieldDeclaration","line":35,"column":4},"2/0/1/3":{"name":"FieldDeclaration","line":35,"column":4},"2/0/1/3":{"name":"FieldDeclaration","line":35,"column":4},"2/0/1/3/0":{"name":"Modifiers","line":35,"column":4},"2/0/1/3/2":{"name":"VariableDeclarator","line":35,"column":19},"2/0/1/4":{"name":"FieldDeclaration","line":36,"column":4},"2/0/1/4":{"name":"FieldDeclaration","line":36,"column":4},"2/0/1/4":{"name":"FieldDeclaration","line":36,"column":4},"2/0/1/4/0":{"name":"Modifiers","line":36,"column":4},"2/0/1/4/2":{"name":"VariableDeclarator","line":36,"column":17},"2/0/1/5/0":{"name":"Modifiers","line":37,"column":4},"2/0/1/5":{"name":"FieldDeclaration","line":37,"column":4},"2/0/1/5":{"name":"FieldDeclaration","line":37,"column":4},"2/0/1/5":{"name":"FieldDeclaration","line":37,"column":4},"2/0/1/5":{"name":"FieldDeclaration","line":37,"column":4},"2/0/1/5/1":{"name":"ReferenceType","line":37,"column":12},"2/0/1/5/2":{"name":"VariableDeclarator","line":37,"column":27},"2/0/1/6":{"name":"FieldDeclaration","line":39,"column":4},"2/0/1/6":{"name":"FieldDeclaration","line":39,"column":4},"2/0/1/6":{"name":"FieldDeclaration","line":39,"column":4},"2/0/1/6/0":{"name":"Modifiers","line":39,"column":4},"2/0/1/6/2":{"name":"VariableDeclarator","line":39,"column":19},"2/0/1/7":{"name":"FieldDeclaration","line":40,"column":4},"2/0/1/7":{"name":"FieldDeclaration","line":40,"column":4},"2/0/1/7":{"name":"FieldDeclaration","line":40,"column":4},"2/0/1/7/0":{"name":"Modifiers","line":40,"column":4},"2/0/1/7/2":{"name":"VariableDeclarator","line":40,"column":19},"2/0/1/8/0":{"name":"Modifiers","line":41,"column":4},"2/0/1/8":{"name":"FieldDeclaration","line":41,"column":4},"2/0/1/8":{"name":"FieldDeclaration","line":41,"column":4},"2/0/1/8":{"name":"FieldDeclaration","line":41,"column":4},"2/0/1/8/2":{"name":"VariableDeclarator","line":41,"column":20},"2/0/1/9/3/0/1/0":{"name":"AssignStatement","line":47,"column":12},"2/0/1/9/3/0/1/0/0/0":{"name":"This","line":47,"column":12},"2/0/1/9/3/0/1/0/0":{"name":"FieldAccess","line":47,"column":12},"2/0/1/9/3/0/1/0/0":{"name":"FieldAccess","line":47,"column":12},"2/0/1/12/3/0/0/0":{"name":"This","line":65,"column":8},"2/0/1/12/3/0/0":{"name":"FieldAccess","line":65,"column":8},"2/0/1/12/3/0/0":{"name":"FieldAccess","line":65,"column":8},"2/0/1/12/3/0":{"name":"AssignStatement","line":65,"column":8},"2/0/1/14/3/0/0/0":{"name":"This","line":76,"column":8},"2/0/1/14/3/0":{"name":"AssignStatement","line":76,"column":8},"2/0/1/14/3/0/0":{"name":"FieldAccess","line":76,"column":8},"2/0/1/14/3/0/0":{"name":"FieldAccess","line":76,"column":8},"2/0/1/15/3/0/0":{"name":"FieldAccess","line":81,"column":8},"2/0/1/15/3/0/0":{"name":"FieldAccess","line":81,"column":8},"2/0/1/15/3/0":{"name":"AssignStatement","line":81,"column":8},"2/0/1/15/3/0/0/0":{"name":"This","line":81,"column":8},"2/0/1/16/3/0/0/0":{"name":"This","line":86,"column":8},"2/0/1/16/3/0/0":{"name":"FieldAccess","line":86,"column":8},"2/0/1/16/3/0/0":{"name":"FieldAccess","line":86,"column":8},"2/0/1/16/3/0":{"name":"AssignStatement","line":86,"column":8},"2/0/1/17/3/0/0/0":{"name":"This","line":91,"column":8},"2/0/1/17/3/0":{"name":"AssignStatement","line":91,"column":8},"2/0/1/17/3/0/0":{"name":"FieldAccess","line":91,"column":8},"2/0/1/17/3/0/0":{"name":"FieldAccess","line":91,"column":8},"2/0/1/18/3":{"name":"MethodBody","line":96,"column":4},"2/0/1/18/3/0":{"name":"IfStatement","line":97,"column":8},"2/0/1/18/3/0/0":{"name":"Eq","line":97,"column":12},"2/0/1/18/3/0/0/0":{"name":"FieldAccess","line":97,"column":12},"2/0/1/18/3/0/0/0":{"name":"FieldAccess","line":97,"column":12},"2/0/1/18/3/0/0/0/0":{"name":"This","line":97,"column":12},"2/0/1/18/3/0/1/0":{"name":"AssignStatement","line":99,"column":12},"2/0/1/18/3/0/1/0/0":{"name":"FieldAccess","line":99,"column":12},"2/0/1/18/3/0/1/0/0":{"name":"FieldAccess","line":99,"column":12},"2/0/1/18/3/0/1/0/0/0":{"name":"This","line":99,"column":12},"2/0/1/18/3/1/0/0":{"name":"FieldAccess","line":101,"column":15},"2/0/1/18/3/1/0/0":{"name":"FieldAccess","line":101,"column":15},"2/0/1/18/3/1/0/0/0":{"name":"This","line":101,"column":15},"2/0/1/18/3/1/0":{"name":"PrimaryMethodInvocation","line":101,"column":15},"2/0/1/19/3":{"name":"MethodBody","line":106,"column":4},"2/0/1/19/3/0":{"name":"IfStatement","line":107,"column":8},"2/0/1/19/3/0/0/0":{"name":"FieldAccess","line":107,"column":12},"2/0/1/19/3/0/0/0":{"name":"FieldAccess","line":107,"column":12},"2/0/1/19/3/0/0":{"name":"Eq","line":107,"column":12},"2/0/1/19/3/0/0/0/0":{"name":"This","line":107,"column":12},"2/0/1/19/3/0/1/0":{"name":"AssignStatement","line":109,"column":12},"2/0/1/19/3/0/1/0/0/0":{"name":"This","line":109,"column":12},"2/0/1/19/3/0/1/0/0":{"name":"FieldAccess","line":109,"column":12},"2/0/1/19/3/0/1/0/0":{"name":"FieldAccess","line":109,"column":12},"2/0/1/19/3/1/0":{"name":"PrimaryMethodInvocation","line":111,"column":15},"2/0/1/19/3/1/0/0":{"name":"FieldAccess","line":111,"column":15},"2/0/1/19/3/1/0/0":{"name":"FieldAccess","line":111,"column":15},"2/0/1/19/3/1/0/0/0":{"name":"This","line":111,"column":15},"2/0/1/20/3":{"name":"MethodBody","line":116,"column":4},"2/0/1/20/3":{"name":"MethodBody","line":116,"column":4},"2/0/1/20/3":{"name":"MethodBody","line":116,"column":4},"2/0/1/20/3":{"name":"MethodBody","line":116,"column":4},"2/0/1/20/3":{"name":"MethodBody","line":116,"column":4},"2/0/1/20/3":{"name":"MethodBody","line":116,"column":4},"2/0/1/20/3":{"name":"MethodBody","line":116,"column":4},"2/0/1/20/3/0":{"name":"IfStatement","line":117,"column":8},"2/0/1/20/3/0/0/0/0/0":{"name":"FieldAccess","line":117,"column":12},"2/0/1/20/3/0/0/0/0":{"name":"Eq","line":117,"column":12},"2/0/1/20/3/0/0/0/1/0":{"name":"FieldAccess","line":117,"column":33},"2/0/1/20/3/0/0/0/1":{"name":"Eq","line":117,"column":33},"2/0/1/20/3/0/0/1/0":{"name":"FieldAccess","line":117,"column":49},"2/0/1/20/3/0/0/1":{"name":"Eq","line":117,"column":49},"2/0/1/20/3/1":{"name":"IfStatement","line":122,"column":8},"2/0/1/20/3/1/0/0":{"name":"FieldAccess","line":122,"column":12},"2/0/1/20/3/1/0":{"name":"NotEq","line":122,"column":12},"2/0/1/20/3/1/1":{"name":"Block","line":123,"column":8},"2/0/1/20/3/1/1/0":{"name":"IfStatement","line":124,"column":12},"2/0/1/20/3/1/1/0/0":{"name":"Eq","line":124,"column":16},"2/0/1/20/3/1/1/0/0/0":{"name":"FieldAccess","line":124,"column":16},"2/0/1/20/3/2":{"name":"IfStatement","line":130,"column":8},"2/0/1/20/3/2/0/0":{"name":"FieldAccess","line":130,"column":12},"2/0/1/20/3/2/0":{"name":"NotEq","line":130,"column":12},"2/0/1/20/3/2/1":{"name":"Block","line":131,"column":8},"2/0/1/20/3/2/1/0/0":{"name":"FieldAccess","line":132,"column":12},"2/0/1/20/3/2/1/0/0":{"name":"FieldAccess","line":132,"column":12},"2/0/1/20/3/2/1/0/0/0":{"name":"This","line":132,"column":12},"2/0/1/20/3/2/1/0":{"name":"AssignStatement","line":132,"column":12},"2/0/1/20/3/2/1/0":{"name":"AssignStatement","line":132,"column":12},"2/0/1/20/3/2/1/0/1":{"name":"StandardInstanceCreation","line":132,"column":26},"2/0/1/20/3/2/1/0/1":{"name":"StandardInstanceCreation","line":132,"column":26},"2/0/1/20/3/2/1/0/1":{"name":"StandardInstanceCreation","line":132,"column":26},"2/0/1/20/3/2/1/0/1/0":{"name":"ReferenceType","line":132,"column":30},"2/0/1/20/3/2/1/0/1/1":{"name":"Arguments","line":132,"column":44},"2/0/1/20/3/2/1/0/1/1":{"name":"Arguments","line":132,"column":44},"2/0/1/20/3/2/1/0/1/1":{"name":"Arguments","line":132,"column":44},"2/0/1/20/3/2/1/0/1/1/0":{"name":"SimpleMethodInvocation","line":132,"column":46},"2/0/1/20/3/2/1/0/1/1/0":{"name":"SimpleMethodInvocation","line":132,"column":46},"2/0/1/20/3/2/1/0/1/1/0/0":{"name":"Arguments","line":132,"column":56},"2/0/1/20/3/2/1/0/1/1/1":{"name":"FieldAccess","line":132,"column":60},"2/0/1/20/3/3":{"name":"IfStatement","line":135,"column":8},"2/0/1/20/3/3/0":{"name":"And","line":135,"column":12},"2/0/1/20/3/3/0/0":{"name":"ParenthesizedExpression","line":135,"column":12},"2/0/1/20/3/3/0/0/0/0":{"name":"FieldAccess","line":135,"column":14},"2/0/1/20/3/3/0/0/0":{"name":"NotEq","line":135,"column":14},"2/0/1/20/3/3/0/1/0/0":{"name":"Arguments","line":135,"column":48},"2/0/1/20/3/3/0/1/0/0/0":{"name":"FieldAccess","line":135,"column":50},"2/0/1/20/3/3/1/0/1/0/0/0":{"name":"Add","line":137,"column":31},"2/0/1/20/3/3/1/0/1/0":{"name":"Add","line":137,"column":31},"2/0/1/20/3/3/1/0/1/0/0/0/1":{"name":"FieldAccess","line":137,"column":57},"2/0/1/20/3/3/1/0/1/0/1":{"name":"FieldAccess","line":137,"column":91},"2/0/1/20/3/4":{"name":"IfStatement","line":141,"column":8},"2/0/1/20/3/4/0/0":{"name":"ParenthesizedExpression","line":141,"column":12},"2/0/1/20/3/4/0":{"name":"And","line":141,"column":12},"2/0/1/20/3/4/0/0/0/0":{"name":"FieldAccess","line":141,"column":14},"2/0/1/20/3/4/0/0/0":{"name":"NotEq","line":141,"column":14},"2/0/1/20/3/4/1":{"name":"Block","line":142,"column":8},"2/0/1/20/3/4/1/0":{"name":"IfStatement","line":143,"column":12},"2/0/1/20/3/4/1/0/0/0":{"name":"FieldAccess","line":143,"column":16},"2/0/1/20/3/4/1/0/0":{"name":"NotEq","line":143,"column":16},"2/0/1/20/3/4/1/0/1/0/1/0/0/0":{"name":"Add","line":145,"column":35},"2/0/1/20/3/4/1/0/1/0/1/0/0/0/0/0":{"name":"Add","line":145,"column":35},"2/0/1/20/3/4/1/0/1/0/1/0":{"name":"Add","line":145,"column":35},"2/0/1/20/3/4/1/0/1/0/1/0/0/0/0/0/1":{"name":"FieldAccess","line":145,"column":55},"2/0/1/20/3/4/1/0/1/0/1/0/0/0/1":{"name":"FieldAccess","line":145,"column":68},"2/0/1/20/3/4/1/0/1/0/1/0/1":{"name":"FieldAccess","line":145,"column":97},"2/0/1/20/3/4/1/0/2/0/1/0":{"name":"Add","line":149,"column":35},"2/0/1/20/3/4/1/0/2/0/1/0/0/0":{"name":"Add","line":149,"column":35},"2/0/1/20/3/4/1/0/2/0/1/0/0/0/1":{"name":"FieldAccess","line":149,"column":55},"2/0/1/20/3/4/1/0/2/0/1/0/1":{"name":"FieldAccess","line":149,"column":84},"2/0/1/20/3/5":{"name":"IfStatement","line":154,"column":8},"2/0/1/20/3/5/0":{"name":"And","line":154,"column":12},"2/0/1/20/3/5/0/0":{"name":"ParenthesizedExpression","line":154,"column":12},"2/0/1/20/3/5/0/0/0":{"name":"NotEq","line":154,"column":14},"2/0/1/20/3/5/0/0/0/0":{"name":"FieldAccess","line":154,"column":14},"2/0/1/20/3/5/0/1/0/0":{"name":"Arguments","line":154,"column":50},"2/0/1/20/3/5/0/1/0/0/0":{"name":"FieldAccess","line":154,"column":52},"2/0/1/20/3/5/1/0/1/0/0/0":{"name":"Add","line":156,"column":31},"2/0/1/20/3/5/1/0/1/0":{"name":"Add","line":156,"column":31},"2/0/1/20/3/5/1/0/1/0/0/0/1":{"name":"FieldAccess","line":156,"column":60},"2/0/1/20/3/5/1/0/1/0/1":{"name":"FieldAccess","line":156,"column":93},"2/0/1/20/3/6":{"name":"IfStatement","line":160,"column":8},"2/0/1/21/3":{"name":"MethodBody","line":170,"column":4},"2/0/1/21/3/0":{"name":"IfStatement","line":171,"column":8},"2/0/1/21/3/0/0":{"name":"Eq","line":171,"column":12},"2/0/1/21/3/0/0/0":{"name":"FieldAccess","line":171,"column":12},"2/0/1/21/3/1/1":{"name":"Block","line":177,"column":8},"2/0/1/21/3/1/1/1":{"name":"IfStatement","line":179,"column":12},"2/0/1/21/3/1/1/1/0/1/1":{"name":"Arguments","line":179,"column":48},"2/0/1/21/3/1/1/1/0/1/1/0":{"name":"FieldAccess","line":179,"column":50},"2/0/1/21/3/1/1/1/1/0/0":{"name":"Arguments","line":181,"column":27},"2/0/1/21/3/1/1/1/1/0/0":{"name":"Arguments","line":181,"column":27},"2/0/1/21/3/1/1/1/1/0/0/0":{"name":"FieldAccess","line":181,"column":29},"2/0/1/21/3/1/1/1/1/0/0/1":{"name":"FieldAccess","line":181,"column":39},"2/0/1/22/3/0/0":{"name":"Block","line":190,"column":8},"2/0/1/22/3/0/0/0":{"name":"IfStatement","line":191,"column":12},"2/0/1/22/3/0/0/0/2":{"name":"Block","line":196,"column":12},"2/0/1/22/3/0/0/0/2":{"name":"Block","line":196,"column":12},"2/0/1/22/3/0/0/0/2/0":{"name":"LocalVariableDeclarationStatement","line":197,"column":16},"2/0/1/22/3/0/0/0/2/0":{"name":"LocalVariableDeclarationStatement","line":197,"column":16},"2/0/1/22/3/0/0/0/2/0":{"name":"LocalVariableDeclarationStatement","line":197,"column":16},"2/0/1/22/3/0/0/0/2/0":{"name":"LocalVariableDeclarationStatement","line":197,"column":16},"2/0/1/22/3/0/0/0/2/0/1":{"name":"VariableDeclarator","line":197,"column":28},"2/0/1/22/3/0/0/0/2/0/1":{"name":"VariableDeclarator","line":197,"column":28},"2/0/1/22/3/0/0/0/2/0/1/0/0":{"name":"PrimaryMethodInvocation","line":197,"column":32},"2/0/1/22/3/0/0/0/2/0/1/0":{"name":"PrimaryMethodInvocation","line":197,"column":32},"2/0/1/22/3/0/0/0/2/0/1/0":{"name":"PrimaryMethodInvocation","line":197,"column":32},"2/0/1/22/3/0/0/0/2/1/1":{"name":"Block","line":201,"column":16},"2/0/1/22/3/0/0/0/2/1/1/0":{"name":"PrimaryMethodInvocationStatement","line":202,"column":20},"2/0/1/22/3/0/0/0/2/1/1/0":{"name":"PrimaryMethodInvocationStatement","line":202,"column":20},"2/0/1/22/3/0/0/0/2/1/1/0/0":{"name":"Name","line":202,"column":20},"2/0/1/23/3":{"name":"MethodBody","line":223,"column":4},"2/0/1/23/3/0":{"name":"IfStatement","line":224,"column":8},"2/0/1/23/3/0/0/0":{"name":"FieldAccess","line":224,"column":12},"2/0/1/23/3/0/0":{"name":"Eq","line":224,"column":12},"2/0/1/23/3/0/1/0/0/0":{"name":"Arguments","line":226,"column":28},"2/0/1/23/3/0/1/0/0/0/0/0":{"name":"Arguments","line":226,"column":41},"2/0/1/23/3/0/1/0/0/0/0/0/0":{"name":"FieldAccess","line":226,"column":43},"2/0/1/23/3/0/1/0/0/0/1":{"name":"FieldAccess","line":226,"column":51},"2/0/1/23/3/0/2/0/1/0/0":{"name":"FieldAccess","line":230,"column":29},"2/0/1/23/3/0/2/0/1/0":{"name":"PrimaryMethodInvocation","line":230,"column":29},"2/0/1/23/3/0/2/1/3":{"name":"Block","line":232,"column":12},"2/0/1/23/3/0/2/1/3":{"name":"Block","line":232,"column":12},"2/0/1/23/3/0/2/1/3/2":{"name":"IfStatement","line":251,"column":16},"2/0/1/23/3/0/2/1/3/2/0/1/0":{"name":"FieldAccess","line":251,"column":37},"2/0/1/23/3/0/2/1/3/2/0/1":{"name":"PrimaryMethodInvocation","line":251,"column":37},"2/0/1/23/3/0/2/1/3/2/1":{"name":"Block","line":252,"column":16},"2/0/1/23/3/0/2/1/3/2/1/0":{"name":"IfStatement","line":253,"column":20},"2/0/1/23/3/0/2/1/3/2/1/0":{"name":"IfStatement","line":253,"column":20},"2/0/1/23/3/0/2/1/3/2/1/0/0":{"name":"Eq","line":253,"column":24},"2/0/1/23/3/0/2/1/3/2/1/0/0/0":{"name":"FieldAccess","line":253,"column":24},"2/0/1/23/3/0/2/1/3/2/1/0/2":{"name":"IfStatement","line":258,"column":25},"2/0/1/23/3/0/2/1/3/2/1/0/2":{"name":"IfStatement","line":258,"column":25},"2/0/1/23/3/0/2/1/3/2/1/0/2/0/0":{"name":"PrimaryMethodInvocation","line":258,"column":29},"2/0/1/23/3/0/2/1/3/2/1/0/2/0/0/0":{"name":"FieldAccess","line":258,"column":29},"2/0/1/23/3/0/2/1/3/2/1/0/2/2":{"name":"IfStatement","line":264,"column":25},"2/0/1/23/3/0/2/1/3/2/1/0/2/2/0/0/0":{"name":"FieldAccess","line":264,"column":29},"2/0/1/23/3/0/2/1/3/2/1/0/2/2/0/0":{"name":"PrimaryMethodInvocation","line":264,"column":29},"2/0/1/23/3/0/2/1/3/4":{"name":"IfStatement","line":276,"column":16},"2/0/1/23/3/0/2/1/3/4/0/1":{"name":"PrimaryMethodInvocation","line":277,"column":23},"2/0/1/23/3/0/2/1/3/4/0/1/0":{"name":"FieldAccess","line":277,"column":23},"2/0/1/23/3/0/2/1/3/4/1":{"name":"Block","line":278,"column":16},"2/0/1/23/3/0/2/1/3/4/1/0":{"name":"IfStatement","line":279,"column":20},"2/0/1/23/3/0/2/1/3/4/1/0":{"name":"IfStatement","line":279,"column":20},"2/0/1/23/3/0/2/1/3/4/1/0/0/0":{"name":"FieldAccess","line":279,"column":24},"2/0/1/23/3/0/2/1/3/4/1/0/0":{"name":"Eq","line":279,"column":24},"2/0/1/23/3/0/2/1/3/4/1/0/2":{"name":"IfStatement","line":284,"column":25},"2/0/1/23/3/0/2/1/3/4/1/0/2/0":{"name":"PrimaryMethodInvocation","line":284,"column":29},"2/0/1/23/3/0/2/1/3/4/1/0/2/0/0":{"name":"FieldAccess","line":284,"column":29},"2/0/1/23/3/0/2/1/3/5/1":{"name":"Block","line":295,"column":16},"2/0/1/23/3/0/2/1/3/5/1/0":{"name":"IfStatement","line":296,"column":20},"2/0/1/23/3/0/2/1/3/5/1/0/0/0/0/1":{"name":"Arguments","line":296,"column":43},"2/0/1/23/3/0/2/1/3/5/1/0/0/0/0/1/1":{"name":"FieldAccess","line":296,"column":51},"2/0/1/23/3/0/2/1/3/5/1/0/0/0/1/0":{"name":"Add","line":297,"column":35},"2/0/1/23/3/0/2/1/3/5/1/0/0/0/1/0/0":{"name":"FieldAccess","line":297,"column":35},"2/0/1/23/3/0/2/1/3/6/1":{"name":"Block","line":305,"column":16},"2/0/1/23/3/0/2/1/3/6/1/0":{"name":"IfStatement","line":306,"column":20},"2/0/1/23/3/0/2/1/3/6/1/0/0/0/0/1":{"name":"Arguments","line":306,"column":43},"2/0/1/23/3/0/2/1/3/6/1/0/0/0/0/1/1":{"name":"FieldAccess","line":306,"column":53},"2/0/1/23/3/0/2/1/3/6/1/0/0/0/1/0":{"name":"Add","line":307,"column":35},"2/0/1/23/3/0/2/1/3/6/1/0/0/0/1/0/0":{"name":"FieldAccess","line":307,"column":35},"2/0/1/23/3/0/2/1/3/7/1/1/1":{"name":"Block","line":318,"column":20},"2/0/1/23/3/0/2/1/3/7/1/1/1/0":{"name":"IfStatement","line":319,"column":24},"2/0/1/23/3/0/2/1/3/7/1/1/1/0/0/0/0/1":{"name":"Arguments","line":319,"column":47},"2/0/1/23/3/0/2/1/3/7/1/1/1/0/0/0/0/1/1":{"name":"FieldAccess","line":319,"column":62},"2/0/1/23/3/0/2/1/3/7/1/1/1/0/0/0/1/0/0":{"name":"FieldAccess","line":320,"column":39},"2/0/1/23/3/0/2/1/3/7/1/1/1/0/0/0/1/0":{"name":"Add","line":320,"column":39},"2/0/1/24/3":{"name":"MethodBody","line":332,"column":4},"2/0/1/24/3/0":{"name":"IfStatement","line":333,"column":8},"2/0/1/24/3/0/0":{"name":"NotEq","line":333,"column":12},"2/0/1/24/3/0/0/0":{"name":"FieldAccess","line":333,"column":12},"2/0/1/24/3/0/1":{"name":"Block","line":334,"column":8},"2/0/1/24/3/0/1/0":{"name":"IfStatement","line":335,"column":12},"2/0/1/24/3/0/1/0":{"name":"IfStatement","line":335,"column":12},"2/0/1/24/3/0/1/0/0":{"name":"PrimaryMethodInvocation","line":335,"column":16},"2/0/1/24/3/0/1/0/0/0":{"name":"FieldAccess","line":335,"column":16},"2/0/1/24/3/0/1/0/2":{"name":"IfStatement","line":343,"column":17},"2/0/1/24/3/0/1/0/2/0":{"name":"PrimaryMethodInvocation","line":343,"column":21},"2/0/1/24/3/0/1/0/2/0/0":{"name":"FieldAccess","line":343,"column":21},"2/0/1/25/3":{"name":"MethodBody","line":360,"column":4},"2/0/1/25/3/0":{"name":"IfStatement","line":361,"column":8},"2/0/1/25/3/0/2":{"name":"Block","line":366,"column":8},"2/0/1/25/3/0/2":{"name":"Block","line":366,"column":8},"2/0/1/25/3/0/2/0":{"name":"LocalVariableDeclarationStatement","line":367,"column":12},"2/0/1/25/3/0/2/0":{"name":"LocalVariableDeclarationStatement","line":367,"column":12},"2/0/1/25/3/0/2/0":{"name":"LocalVariableDeclarationStatement","line":367,"column":12},"2/0/1/25/3/0/2/0":{"name":"LocalVariableDeclarationStatement","line":367,"column":12},"2/0/1/25/3/0/2/0/1":{"name":"VariableDeclarator","line":367,"column":24},"2/0/1/25/3/0/2/0/1":{"name":"VariableDeclarator","line":367,"column":24},"2/0/1/25/3/0/2/0/1/0":{"name":"PrimaryMethodInvocation","line":367,"column":29},"2/0/1/25/3/0/2/0/1/0":{"name":"PrimaryMethodInvocation","line":367,"column":29},"2/0/1/25/3/0/2/0/1/0/0":{"name":"PrimaryMethodInvocation","line":367,"column":29},"2/0/1/25/3/0/2/1/1":{"name":"Block","line":369,"column":12},"2/0/1/25/3/0/2/1/1/0":{"name":"ReturnStatement","line":370,"column":16},"2/0/1/25/3/0/2/1/1/0":{"name":"ReturnStatement","line":370,"column":16},"2/0/1/25/3/0/2/1/1/0/0":{"name":"ParenthesizedExpression","line":370,"column":23},"2/0/1/25/3/0/2/1/1/0/0/0/0":{"name":"PrimaryMethodInvocation","line":370,"column":25},"2/0/1/25/3/0/2/1/1/0/0/0":{"name":"NotEq","line":370,"column":25},"2/0/1/25/3/0/2/1/1/0/0/0":{"name":"NotEq","line":370,"column":25},"2/0/1/25/3/0/2/1/1/0/0/0/0/0":{"name":"Name","line":370,"column":25},"2/0/1/25/3/0/2/1/1/0/0/0/1":{"name":"NullLiteral","line":370,"column":63}}